CHANGES.rst
MANIFEST.in
README.txt
setup.py
collective/__init__.py
collective.multimodeview.egg-info/PKG-INFO
collective.multimodeview.egg-info/SOURCES.txt
collective.multimodeview.egg-info/dependency_links.txt
collective.multimodeview.egg-info/entry_points.txt
collective.multimodeview.egg-info/namespace_packages.txt
collective.multimodeview.egg-info/not-zip-safe
collective.multimodeview.egg-info/requires.txt
collective.multimodeview.egg-info/top_level.txt
collective/multimodeview/__init__.py
collective/multimodeview/configure.zcml
collective/multimodeview/rebuild_i18n.sh
collective/multimodeview/samples.zcml
collective/multimodeview/browser/__init__.py
collective/multimodeview/browser/ajax.py
collective/multimodeview/browser/base.py
collective/multimodeview/browser/view.py
collective/multimodeview/browser/viewlet.py
collective/multimodeview/browser/templates/form_extras.pt
collective/multimodeview/locales/collective.multimodeview.pot
collective/multimodeview/locales/manual.pot
collective/multimodeview/locales/en/LC_MESSAGES/collective.multimodeview.mo
collective/multimodeview/locales/en/LC_MESSAGES/collective.multimodeview.po
collective/multimodeview/locales/fr/LC_MESSAGES/collective.multimodeview.mo
collective/multimodeview/locales/fr/LC_MESSAGES/collective.multimodeview.po
collective/multimodeview/locales/nl/LC_MESSAGES/collective.multimodeview.mo
collective/multimodeview/locales/nl/LC_MESSAGES/collective.multimodeview.po
collective/multimodeview/samples/__init__.py
collective/multimodeview/samples/configure.zcml
collective/multimodeview/samples/notes_view.py
collective/multimodeview/samples/sample1.pt
collective/multimodeview/samples/sample2.pt
collective/multimodeview/samples/sample21.pt
collective/multimodeview/samples/sample3.pt
collective/multimodeview/samples/views.py
docs/INSTALL.txt
docs/LICENSE.GPL
docs/LICENSE.txt