Metadata-Version: 1.1
Name: collective.multimodeview
Version: 0.3
Summary: Simple package to manage views with multiple modes.
Home-page: https://github.com/zestsoftware/collective.multimodeview
Author: Zest Software
Author-email: info@zestsoftware.nl
License: GPL
Keywords: multimode view
Platform: UNKNOWN
Classifier: Framework :: Plone
Classifier: Framework :: Plone :: 3.3
Classifier: Programming Language :: Python
Classifier: Programming Language :: Python :: 2.4
